try_pkg/__init__.py
try_pkg/app.py
try_pkg/colors.py
try_pkg/getdata.py
try_script-1.6.dist-info/METADATA
try_script-1.6.dist-info/RECORD
try_script-1.6.dist-info/WHEEL
try_script-1.6.dist-info/entry_points.txt
try_script-1.6.dist-info/top_level.txt
