Metadata-Version: 2.1
Name: try-script
Version: 1.6
Summary: Just script that helps me learn foreign languages,
Home-page: https://github.com.jankaifer/app.py
Author: Jan Kaifer
Author-email: kaifer741@gamil.com
License: UNKNOWN
Keywords: learning,school,german,english,awesome
Platform: UNKNOWN
